ibmcloudenv/IBMCloudEnv.py
ibmcloudenv/__init__.py
ibmcloudenv-0.2.1.dist-info/DESCRIPTION.rst
ibmcloudenv-0.2.1.dist-info/METADATA
ibmcloudenv-0.2.1.dist-info/RECORD
ibmcloudenv-0.2.1.dist-info/WHEEL
ibmcloudenv-0.2.1.dist-info/metadata.json
ibmcloudenv-0.2.1.dist-info/top_level.txt
